dora_rerun/__init__.py
dora_rerun/dora_rerun.cp314t-win_amd64.pyd
dora_rerun-0.4.1.dist-info/METADATA
dora_rerun-0.4.1.dist-info/WHEEL
dora_rerun-0.4.1.dist-info/entry_points.txt
dora_rerun-0.4.1.dist-info/RECORD
