Metadata-Version: 2.4
Name: dora-rerun
Version: 0.4.1
Requires-Dist: rerun-loader-urdf
Requires-Dist: rerun-sdk>=0.24.0
Requires-Dist: robot-descriptions
License: MIT
Requires-Python: >=3.10
